[
    {
        "firebase_id": "yXbHXGB1",
        "name": "Brianna Washington",
        "profile_pic": "https://i.pinimg.com/originals/2f/15/f2/2f15f2e8c688b3120d3d26467b06330c.jpg",
        "selected_tags": {
            "language": [
                "Spanish",
                "Hindi",
                "Russian"
            ],
            "smoker": "Smoker",
            "pets": "Cat-friendly",
            "diet": "Vegan",
            "allergies": "Peanuts",
            "habit": "Morning-bird",
            "work": "Night-worker"
        },
        "phone_number": "001-287-955-4194x9344",
        "bio": "Can major respond friend. Condition without time country effort house news.\nBillion challenge call gas chance answer.\nRelationship gas compare war. Chance mind fight how.",
        "liked_properties": [
            "219117658",
            "219230190",
            "219254730",
            "219233714",
            "219213318",
            "219210969",
            "219173583",
            "219242930",
            "25591329",
            "29106331",
            "217020500",
            "25624305",
            "219226895",
            "219239612",
            "219236237",
            "217283526",
            "218618289",
            "219136282",
            "219173975",
            "219249766",
            "219038703",
            "219239624",
            "219247321",
            "219236237",
            "219178847",
            "219009409",
            "219204122",
            "219217204",
            "25647407",
            "219198157",
            "219254692",
            "219226907",
            "219163859",
            "219032881",
            "219006379",
            "219246461",
            "219132939",
            "219106038",
            "219201538"
        ],
        "liked_users": [
            "93683175",
            "89749581",
            "90611943",
            "46315047",
            "79258014",
            "57912130",
            "77347857",
            "32260664",
            "82063414"
        ]
    },
    {
        "firebase_id": "YhG6rT19",
        "name": "Gregory Lester",
        "profile_pic": "https://i.pinimg.com/originals/2f/15/f2/2f15f2e8c688b3120d3d26467b06330c.jpg",
        "selected_tags": {
            "language": [
                "Russian",
                "Chinese"
            ],
            "smoker": "Non-smoker",
            "pets": "Dog-friendly",
            "diet": "Vegetarian",
            "allergies": "Peanuts",
            "habit": "Night-owl",
            "work": "Night-worker"
        },
        "phone_number": "269-300-6620x9126",
        "bio": "Skin mother across will.\nAgency court worry else prevent carry. Exist forward away middle here. Likely interest travel show discuss. Region surface exactly.",
        "liked_properties": [
            "25541132",
            "217811739",
            "219066994",
            "215256248",
            "22045681",
            "219237383",
            "219233878",
            "219225302",
            "25571576",
            "219249606",
            "25631866",
            "219192089",
            "25568449",
            "26115508",
            "25624305",
            "219146938",
            "219143968",
            "219042647",
            "219204122",
            "216314376"
        ],
        "liked_users": [
            "19223829"
        ]
    },
    {
        "firebase_id": "d6t3sLMb",
        "name": "Jonathan Brown",
        "profile_pic": "https://i.pinimg.com/originals/2f/15/f2/2f15f2e8c688b3120d3d26467b06330c.jpg",
        "selected_tags": {
            "language": [
                "Portuguese",
                "Russian"
            ],
            "smoker": "Non-smoker",
            "pets": "No-pets",
            "diet": "Vegan",
            "allergies": "Shellfish",
            "habit": "Night-owl",
            "work": "Night-worker"
        },
        "phone_number": "+1-963-844-2487x308",
        "bio": "Expect American officer group. Radio society investment paper.\nUnderstand beat itself. Want effort already camera put already music. Effort fine because.",
        "liked_properties": [
            "219143978",
            "219185080",
            "219252379"
        ],
        "liked_users": [
            "57572668",
            "69501528"
        ]
    },
    {
        "firebase_id": "tiOebgRb",
        "name": "Kenneth Hernandez",
        "profile_pic": "https://i.pinimg.com/originals/2f/15/f2/2f15f2e8c688b3120d3d26467b06330c.jpg",
        "selected_tags": {
            "language": [
                "Chinese"
            ],
            "smoker": "Smoker",
            "pets": "Dog-friendly",
            "diet": "Vegetarian",
            "allergies": "Peanuts",
            "habit": "Night-owl",
            "work": "Work-from-home"
        },
        "phone_number": "001-224-688-1274",
        "bio": "Kind past increase. Resource responsibility suddenly. Out out power property respond lay.\nCover by attention child. Her leave still view. Either husband name true loss score enough unit.",
        "liked_properties": [
            "219191453",
            "218998352",
            "219254698",
            "218606960",
            "25641525",
            "28267267",
            "25554651",
            "219052323",
            "219185080",
            "219226897",
            "25591329",
            "25633399",
            "219236821",
            "218986097"
        ],
        "liked_users": [
            "29721966",
            "54635359",
            "79980664",
            "63052236",
            "20076814",
            "42993352",
            "27691167",
            "73221982",
            "72595755",
            "29750606"
        ]
    },
    {
        "firebase_id": "VjbEwFhd",
        "name": "Emily Mcdonald",
        "profile_pic": "https://i.pinimg.com/originals/2f/15/f2/2f15f2e8c688b3120d3d26467b06330c.jpg",
        "selected_tags": {
            "language": [
                "French",
                "Spanish"
            ],
            "smoker": "Social smoker",
            "pets": "Cat-friendly",
            "diet": "Vegetarian",
            "allergies": "Shellfish",
            "habit": "Night-owl",
            "work": "Work-from-home"
        },
        "phone_number": "(725)975-1592",
        "bio": "Bank chance thought maintain. Author doctor I these message maintain. Artist area toward professor national early.",
        "liked_properties": [
            "25646801",
            "25627804",
            "218523203",
            "219128718",
            "219032272",
            "219206164",
            "219141046",
            "25607542",
            "217613262",
            "213918736",
            "214224434",
            "219237381",
            "25639992",
            "25647277",
            "218792247",
            "219204155",
            "25540223",
            "219118194",
            "23894825",
            "219075489",
            "219197105",
            "25639619",
            "25554651",
            "219178848",
            "219180267",
            "219178309",
            "25562992"
        ],
        "liked_users": [
            "36607262",
            "86753655",
            "64991514",
            "98722834",
            "44567748"
        ]
    },
    {
        "firebase_id": "qeHaDTuD",
        "name": "Richard Brown",
        "profile_pic": "https://i.pinimg.com/originals/2f/15/f2/2f15f2e8c688b3120d3d26467b06330c.jpg",
        "selected_tags": {
            "language": [
                "English"
            ],
            "smoker": "Smoker",
            "pets": "Dog-friendly",
            "diet": "Vegetarian",
            "allergies": "Peanuts",
            "habit": "Morning-bird",
            "work": "Night-worker"
        },
        "phone_number": "+1-948-853-1367x209",
        "bio": "Prove exist away large require him. Traditional support most service local drug painting. Role send hot describe do around idea.\nDaughter that those lay. Least food way he special left.",
        "liked_properties": [
            "217803662",
            "219010524",
            "217999289",
            "219000704"
        ],
        "liked_users": [
            "37453351",
            "17358915",
            "21213327",
            "43347466",
            "28138359",
            "53652674",
            "51581745",
            "90374459"
        ]
    },
    {
        "firebase_id": "35mNy2SR",
        "name": "Tom Roberts",
        "profile_pic": "https://i.pinimg.com/originals/2f/15/f2/2f15f2e8c688b3120d3d26467b06330c.jpg",
        "selected_tags": {
            "language": [
                "Chinese",
                "Hindi"
            ],
            "smoker": "Smoker",
            "pets": "No-pets",
            "diet": "Vegetarian",
            "allergies": "Shellfish",
            "habit": "Morning-bird",
            "work": "Work-from-home"
        },
        "phone_number": "(529)966-5485x3456",
        "bio": "Ability interview majority size. White magazine design.\nSometimes us card end most society.\nMarket process opportunity ok between. Church list hit put news.",
        "liked_properties": [
            "219246027",
            "219236230",
            "219065973",
            "219146142",
            "25582749",
            "218980689",
            "219230736",
            "219098191",
            "219163859",
            "213896252",
            "219231313",
            "219256340",
            "25615762",
            "25639600",
            "218176853",
            "219204156",
            "25647308",
            "219009409",
            "219000704",
            "219255776",
            "219149614"
        ],
        "liked_users": [
            "20933108",
            "66130231",
            "44610752",
            "40592745",
            "27508682",
            "59383993",
            "84890528",
            "26554992"
        ]
    },
    {
        "firebase_id": "FvmnN4oE",
        "name": "Kathryn Lawrence",
        "profile_pic": "https://i.pinimg.com/originals/2f/15/f2/2f15f2e8c688b3120d3d26467b06330c.jpg",
        "selected_tags": {
            "language": [
                "French",
                "Spanish",
                "English"
            ],
            "smoker": "Smoker",
            "pets": "Dog-friendly",
            "diet": "Vegetarian",
            "allergies": "Shellfish",
            "habit": "Night-owl",
            "work": "Night-worker"
        },
        "phone_number": "(861)446-8291x191",
        "bio": "Customer example huge include single site. Occur standard technology positive.\nPlay spend approach north process suffer. Such campaign eight born born claim. Allow professor value when everything.",
        "liked_properties": [
            "25633420",
            "219100301",
            "219185080",
            "214224437",
            "216024893",
            "218717254",
            "25632493",
            "25631182",
            "25644743",
            "219210997",
            "219159431",
            "25540327",
            "219060109",
            "25642315",
            "219249606",
            "218965253",
            "914321284",
            "218919940",
            "22028036",
            "21980715",
            "218583076",
            "219236289",
            "219204119",
            "25645717",
            "219233714",
            "219143978",
            "25647150",
            "219018065",
            "219232121",
            "219205360",
            "219207254"
        ],
        "liked_users": [
            "93571752",
            "76892386",
            "22920340",
            "33754709"
        ]
    },
    {
        "firebase_id": "2Z2qdDCL",
        "name": "Robert Brown",
        "profile_pic": "https://i.pinimg.com/originals/2f/15/f2/2f15f2e8c688b3120d3d26467b06330c.jpg",
        "selected_tags": {
            "language": [
                "English",
                "Spanish"
            ],
            "smoker": "Social smoker",
            "pets": "No-pets",
            "diet": "Vegetarian",
            "allergies": "Peanuts",
            "habit": "Morning-bird",
            "work": "Work-from-home"
        },
        "phone_number": "001-596-279-4697x2565",
        "bio": "Attention within quite have maintain. Design record parent marriage. Firm fight energy car environmental attention continue. Manager all safe now century.\nSource foreign stock reflect.",
        "liked_properties": [
            "25638940",
            "26577786",
            "218523203",
            "219237382",
            "25648083",
            "219164565",
            "219256907",
            "216492561",
            "214632534",
            "218965253",
            "219212634",
            "219177743",
            "219255310",
            "219237383",
            "25600022",
            "219214580",
            "219026881",
            "219085079",
            "213598365",
            "219113269",
            "219236237",
            "22029042",
            "218697840",
            "219256777",
            "219180060",
            "25629521",
            "219204156",
            "25631918",
            "25609199",
            "25352704",
            "25562992",
            "219229581",
            "22045683",
            "219139065"
        ],
        "liked_users": [
            "22049566",
            "74216674",
            "95473992"
        ]
    },
    {
        "firebase_id": "Tuob3Xue",
        "name": "Katherine Collins",
        "profile_pic": "https://i.pinimg.com/originals/2f/15/f2/2f15f2e8c688b3120d3d26467b06330c.jpg",
        "selected_tags": {
            "language": [
                "Spanish",
                "Chinese",
                "Hindi"
            ],
            "smoker": "Smoker",
            "pets": "No-pets",
            "diet": "Vegetarian",
            "allergies": "Shellfish",
            "habit": "Night-owl",
            "work": "Work-from-home"
        },
        "phone_number": "967.289.1828x32784",
        "bio": "People strong sure house decision. Scene should beautiful thousand will run.\nContain language go woman certain career feeling. Minute big special painting. Health employee total might remember.",
        "liked_properties": [
            "216706908",
            "219244202",
            "219082796",
            "219159431",
            "26577786",
            "219230784",
            "219210978",
            "219204122",
            "219197111",
            "219245238",
            "22028036",
            "26115507",
            "214138461",
            "25641525",
            "219247313",
            "219232817",
            "25627372",
            "219093768",
            "23894825",
            "219214583",
            "219128193",
            "219069593",
            "219256342",
            "217929906",
            "22076152",
            "22029042",
            "219238539",
            "25560545",
            "219198157"
        ],
        "liked_users": [
            "31240988",
            "89409466",
            "11677910",
            "60069320",
            "56653898",
            "58006924",
            "85259398"
        ]
    },
    {
        "firebase_id": "x5TVuSsk",
        "name": "William Smith",
        "profile_pic": "https://i.pinimg.com/originals/2f/15/f2/2f15f2e8c688b3120d3d26467b06330c.jpg",
        "selected_tags": {
            "language": [
                "Spanish"
            ],
            "smoker": "Non-smoker",
            "pets": "No-pets",
            "diet": "Vegan",
            "allergies": "Shellfish",
            "habit": "Night-owl",
            "work": "Night-worker"
        },
        "phone_number": "(794)726-7788",
        "bio": "Each child near green. Side like head current himself site together.\nOver garden field thought including parent. Herself role home.\nAttack loss will of quickly. Plant occur two despite.",
        "liked_properties": [
            "219078361",
            "219205307",
            "217310265",
            "218620159",
            "25888168",
            "25646801",
            "219144629",
            "219065973",
            "219230190",
            "25352704",
            "25606548",
            "29106331",
            "219173575",
            "219060109",
            "213598364",
            "219177754",
            "214224434",
            "217999289"
        ],
        "liked_users": [
            "89827931",
            "38136535",
            "24384146",
            "21478687"
        ]
    },
    {
        "firebase_id": "GoCrCRrQ",
        "name": "Gabriel Steele",
        "profile_pic": "https://i.pinimg.com/originals/2f/15/f2/2f15f2e8c688b3120d3d26467b06330c.jpg",
        "selected_tags": {
            "language": [
                "Chinese",
                "French"
            ],
            "smoker": "Social smoker",
            "pets": "Dog-friendly",
            "diet": "Vegetarian",
            "allergies": "Shellfish",
            "habit": "Morning-bird",
            "work": "Night-worker"
        },
        "phone_number": "001-807-849-6474x173",
        "bio": "Natural mention mother such heart least. Identify seem economic listen arrive question market. Away glass order huge since order window. Have today nice writer wife network.",
        "liked_properties": [
            "219095936",
            "25601216",
            "219070235",
            "216590723",
            "219225302",
            "25644904",
            "25607542",
            "219038775",
            "25625338",
            "219176117",
            "219226895"
        ],
        "liked_users": [
            "89838421",
            "38667737",
            "59028573",
            "53477561",
            "45511489",
            "64923716",
            "59708253",
            "11392662",
            "38159725"
        ]
    },
    {
        "firebase_id": "tYowHXYG",
        "name": "Nicholas Wolf",
        "profile_pic": "https://i.pinimg.com/originals/2f/15/f2/2f15f2e8c688b3120d3d26467b06330c.jpg",
        "selected_tags": {
            "language": [
                "Portuguese",
                "Chinese",
                "French"
            ],
            "smoker": "Smoker",
            "pets": "Dog-friendly",
            "diet": "Vegan",
            "allergies": "Shellfish",
            "habit": "Morning-bird",
            "work": "Work-from-home"
        },
        "phone_number": "945.422.6139",
        "bio": "Anything series edge he. Catch my early long save. Chair glass sure door international.",
        "liked_properties": [
            "219128719",
            "218606960",
            "218732301",
            "219247317",
            "219155042",
            "218523203",
            "218955938",
            "219237383",
            "25622014",
            "219000704",
            "25572435",
            "219134269",
            "219212634",
            "219256633",
            "218663166",
            "219216446",
            "215133676",
            "219183823",
            "25643387",
            "219237390",
            "25647308",
            "219124039",
            "23103565",
            "213841930",
            "25647150",
            "219124574",
            "25646015",
            "219175427",
            "215131446",
            "213917019",
            "218882242",
            "219006379",
            "25618329",
            "25572201",
            "218995349"
        ],
        "liked_users": [
            "57977904",
            "84385128",
            "50520469",
            "76359293",
            "22442801",
            "73627457",
            "23517201"
        ]
    },
    {
        "firebase_id": "GGjMkQ6n",
        "name": "Alexander Villarreal",
        "profile_pic": "https://i.pinimg.com/originals/2f/15/f2/2f15f2e8c688b3120d3d26467b06330c.jpg",
        "selected_tags": {
            "language": [
                "Spanish"
            ],
            "smoker": "Smoker",
            "pets": "No-pets",
            "diet": "Vegan",
            "allergies": "Peanuts",
            "habit": "Night-owl",
            "work": "Night-worker"
        },
        "phone_number": "278.407.3060",
        "bio": "News day her produce learn avoid international. Political meet seat citizen task rich look. Anyone soldier within newspaper truth.",
        "liked_properties": [
            "25644924",
            "25641377",
            "25609199",
            "25574107",
            "217022341",
            "219193754",
            "219175373",
            "219207085",
            "219049492",
            "219205307",
            "219139742",
            "24779517",
            "29106331",
            "25579523",
            "25644743",
            "219197679",
            "219038775",
            "219161022",
            "219148148",
            "219069102",
            "219217204",
            "219233826",
            "219181598",
            "28265481",
            "25620320",
            "218859885",
            "219162833",
            "219190098",
            "25638080",
            "218523203",
            "25638606",
            "25581194",
            "219178846",
            "26115508"
        ],
        "liked_users": [
            "93828736",
            "95683180"
        ]
    },
    {
        "firebase_id": "GGMnDHJe",
        "name": "Michael Conway",
        "profile_pic": "https://i.pinimg.com/originals/2f/15/f2/2f15f2e8c688b3120d3d26467b06330c.jpg",
        "selected_tags": {
            "language": [
                "English",
                "French",
                "Chinese"
            ],
            "smoker": "Non-smoker",
            "pets": "Dog-friendly",
            "diet": "Vegan",
            "allergies": "Shellfish",
            "habit": "Night-owl",
            "work": "Work-from-home"
        },
        "phone_number": "674-838-5556x5466",
        "bio": "Several system ok draw. Carry strong work what positive lawyer notice.\nHuge technology next difference history scientist.\nBehavior past board again. Task man poor.",
        "liked_properties": [
            "219239624",
            "219078361",
            "219015918",
            "219064386",
            "219212634",
            "219226896",
            "219247313",
            "25587062",
            "219106047",
            "213598365",
            "219193183",
            "219224821",
            "214675654",
            "219199472",
            "219226851",
            "219249623",
            "219225943",
            "219139066",
            "213841930"
        ],
        "liked_users": [
            "85453813",
            "12569771",
            "26804945"
        ]
    },
    {
        "firebase_id": "uTAKnhkW",
        "name": "Jennifer Walker",
        "profile_pic": "https://i.pinimg.com/originals/2f/15/f2/2f15f2e8c688b3120d3d26467b06330c.jpg",
        "selected_tags": {
            "language": [
                "Spanish",
                "Chinese",
                "Portuguese"
            ],
            "smoker": "Social smoker",
            "pets": "No-pets",
            "diet": "Vegan",
            "allergies": "Peanuts",
            "habit": "Night-owl",
            "work": "Night-worker"
        },
        "phone_number": "001-885-219-2046x53526",
        "bio": "Though mouth mouth factor energy. Statement mission short front society son cause. Turn challenge two hit weight surface.",
        "liked_properties": [
            "25621903",
            "27597305",
            "214808037",
            "219255313",
            "219247129",
            "219016550",
            "25624004",
            "219244202",
            "218450508",
            "219224127",
            "219053063",
            "219254712",
            "25636616",
            "219184428",
            "25574947",
            "219094935",
            "25647150",
            "219141050",
            "25639882",
            "25629396"
        ],
        "liked_users": []
    },
    {
        "firebase_id": "ZX8aK5L0",
        "name": "George Anderson",
        "profile_pic": "https://i.pinimg.com/originals/2f/15/f2/2f15f2e8c688b3120d3d26467b06330c.jpg",
        "selected_tags": {
            "language": [
                "English",
                "Hindi"
            ],
            "smoker": "Non-smoker",
            "pets": "No-pets",
            "diet": "Vegetarian",
            "allergies": "Peanuts",
            "habit": "Morning-bird",
            "work": "Night-worker"
        },
        "phone_number": "756.874.4799x737",
        "bio": "Arm media many major. Unit take goal north.\nSay much hospital first their fear.\nCompare every these fall fill environment cold. Price support policy color.",
        "liked_properties": [
            "219230187",
            "219178848",
            "218176856",
            "219237382",
            "25574107",
            "25631182",
            "219212600",
            "218034906",
            "219214282",
            "219026881",
            "216314376",
            "219121949",
            "217196215",
            "219223863",
            "219230763",
            "21980258",
            "219236237",
            "219058061",
            "219092661",
            "217613337",
            "219233236",
            "219180060",
            "25627325",
            "219219781",
            "219254692",
            "219246611",
            "25641377",
            "219233864",
            "215131446",
            "219182101",
            "219111439",
            "25624024",
            "25631281",
            "25632493",
            "27505267",
            "218778913",
            "25591329",
            "219226895",
            "219144629",
            "22046046",
            "219234823",
            "219178309",
            "25635311",
            "219226898"
        ],
        "liked_users": []
    },
    {
        "firebase_id": "HVWW58hQ",
        "name": "James Thomas",
        "profile_pic": "https://i.pinimg.com/originals/2f/15/f2/2f15f2e8c688b3120d3d26467b06330c.jpg",
        "selected_tags": {
            "language": [
                "Russian",
                "English",
                "Spanish"
            ],
            "smoker": "Smoker",
            "pets": "No-pets",
            "diet": "Vegetarian",
            "allergies": "Shellfish",
            "habit": "Night-owl",
            "work": "Night-worker"
        },
        "phone_number": "4478751484",
        "bio": "Feeling home bank trip campaign little. From activity against matter simple all. Want compare grow drop resource figure get. Assume air various thousand ask pay owner.",
        "liked_properties": [
            "219193183",
            "22046323",
            "25641346",
            "217999289",
            "25582749",
            "219173928",
            "219244202",
            "218791787",
            "215256248",
            "218782791",
            "217022343",
            "219208609",
            "214435847",
            "219071818",
            "218790911",
            "25572435",
            "219255310"
        ],
        "liked_users": [
            "95625192"
        ]
    },
    {
        "firebase_id": "c7bCdn9I",
        "name": "Matthew Smith",
        "profile_pic": "https://i.pinimg.com/originals/2f/15/f2/2f15f2e8c688b3120d3d26467b06330c.jpg",
        "selected_tags": {
            "language": [
                "French",
                "Chinese"
            ],
            "smoker": "Social smoker",
            "pets": "Cat-friendly",
            "diet": "Vegetarian",
            "allergies": "Shellfish",
            "habit": "Night-owl",
            "work": "Work-from-home"
        },
        "phone_number": "+1-207-529-3750x953",
        "bio": "Among national note base design. Task alone it politics use they.\nSize system education still. Service interview draw none. Individual spend sell five protect dream.",
        "liked_properties": [
            "219065973",
            "25646474",
            "219085079",
            "219198852",
            "216706908",
            "219121949",
            "217022343",
            "219139065",
            "219238534",
            "219162833"
        ],
        "liked_users": [
            "47475200"
        ]
    },
    {
        "firebase_id": "fckijFbD",
        "name": "Michael Davenport",
        "profile_pic": "https://i.pinimg.com/originals/2f/15/f2/2f15f2e8c688b3120d3d26467b06330c.jpg",
        "selected_tags": {
            "language": [
                "Russian",
                "Chinese",
                "Hindi"
            ],
            "smoker": "Smoker",
            "pets": "Dog-friendly",
            "diet": "Vegetarian",
            "allergies": "Shellfish",
            "habit": "Morning-bird",
            "work": "Night-worker"
        },
        "phone_number": "(230)883-4163x36444",
        "bio": "Land black star long occur. Easy sell his feel him view quite. Pass low film family action property.",
        "liked_properties": [
            "219016550",
            "23605174",
            "25635311",
            "219227933",
            "219128193",
            "219168233",
            "25636335",
            "25622014"
        ],
        "liked_users": [
            "76851151",
            "38672627",
            "22229322",
            "48738249",
            "59826192"
        ]
    },
    {
        "firebase_id": "BMLKX29M",
        "name": "Wayne Johnston",
        "profile_pic": "https://i.pinimg.com/originals/2f/15/f2/2f15f2e8c688b3120d3d26467b06330c.jpg",
        "selected_tags": {
            "language": [
                "French"
            ],
            "smoker": "Non-smoker",
            "pets": "No-pets",
            "diet": "Vegetarian",
            "allergies": "Shellfish",
            "habit": "Morning-bird",
            "work": "Work-from-home"
        },
        "phone_number": "001-744-730-0044x1046",
        "bio": "According head consumer political this whether our state. Despite turn mind prevent better get for. Skin about already amount pay though. Design seem later student.",
        "liked_properties": [
            "25615870"
        ],
        "liked_users": [
            "95487977"
        ]
    },
    {
        "firebase_id": "yK9OZWtu",
        "name": "Patricia Walls",
        "profile_pic": "https://i.pinimg.com/originals/2f/15/f2/2f15f2e8c688b3120d3d26467b06330c.jpg",
        "selected_tags": {
            "language": [
                "Hindi",
                "Spanish",
                "Russian"
            ],
            "smoker": "Non-smoker",
            "pets": "Dog-friendly",
            "diet": "Vegan",
            "allergies": "Peanuts",
            "habit": "Night-owl",
            "work": "Work-from-home"
        },
        "phone_number": "+1-779-398-8045x52795",
        "bio": "Culture like money education never trip. Peace open can party.\nAir federal worker available. Foot job network evidence.",
        "liked_properties": [
            "219224133",
            "219197101",
            "25574107",
            "25629396",
            "25624024",
            "25571895",
            "219231983",
            "217811739",
            "219084001",
            "219178309",
            "219211343",
            "219193749",
            "219254730",
            "219093768",
            "219207254",
            "219041242",
            "219226347",
            "219033204",
            "25647150",
            "219222794",
            "219217204",
            "219185080",
            "219162833",
            "217538347",
            "25620593"
        ],
        "liked_users": [
            "97737975",
            "74696087",
            "32999891"
        ]
    },
    {
        "firebase_id": "GZcVwEsT",
        "name": "Keith Robinson",
        "profile_pic": "https://i.pinimg.com/originals/2f/15/f2/2f15f2e8c688b3120d3d26467b06330c.jpg",
        "selected_tags": {
            "language": [
                "Portuguese",
                "French",
                "Chinese"
            ],
            "smoker": "Non-smoker",
            "pets": "Cat-friendly",
            "diet": "Vegetarian",
            "allergies": "Shellfish",
            "habit": "Night-owl",
            "work": "Night-worker"
        },
        "phone_number": "001-848-594-6090x3320",
        "bio": "Half every conference resource ago. Modern have trouble face hard.\nForm citizen tax she. Administration wrong all program middle surface strong.",
        "liked_properties": [
            "219032272",
            "219231982",
            "219178309",
            "219109247",
            "219211343",
            "218836926",
            "219173927",
            "219230113",
            "219180060",
            "219236237",
            "219066994",
            "29107110",
            "25571895",
            "21980257",
            "219236274",
            "25615169",
            "25644924",
            "219229582",
            "219254690",
            "213598364",
            "28069375",
            "219207254",
            "219184437",
            "219111439",
            "219243591",
            "218819050",
            "25888168",
            "25647510",
            "219193752",
            "219012470",
            "219155042",
            "219203631",
            "219116397",
            "219046268",
            "219173583",
            "25598088",
            "219197679",
            "217310275",
            "214435847",
            "219247313",
            "219175427",
            "215256248",
            "26115507",
            "219198852",
            "25646801",
            "218722451"
        ],
        "liked_users": [
            "89645899",
            "81212567",
            "55314988"
        ]
    },
    {
        "firebase_id": "3fOXyBTh",
        "name": "Corey Robinson",
        "profile_pic": "https://i.pinimg.com/originals/2f/15/f2/2f15f2e8c688b3120d3d26467b06330c.jpg",
        "selected_tags": {
            "language": [
                "Portuguese",
                "Spanish",
                "Chinese"
            ],
            "smoker": "Smoker",
            "pets": "No-pets",
            "diet": "Vegetarian",
            "allergies": "Peanuts",
            "habit": "Morning-bird",
            "work": "Work-from-home"
        },
        "phone_number": "+1-536-678-3665x49031",
        "bio": "Himself between similar. Pull skin budget environmental old. Show man political strategy film note.",
        "liked_properties": [
            "218643402"
        ],
        "liked_users": [
            "88217499",
            "46107497",
            "14232071",
            "23385978",
            "72232819",
            "49294721"
        ]
    },
    {
        "firebase_id": "NWc3v3zi",
        "name": "Rebecca Lopez",
        "profile_pic": "https://i.pinimg.com/originals/2f/15/f2/2f15f2e8c688b3120d3d26467b06330c.jpg",
        "selected_tags": {
            "language": [
                "Portuguese",
                "English",
                "Spanish"
            ],
            "smoker": "Smoker",
            "pets": "Cat-friendly",
            "diet": "Vegetarian",
            "allergies": "Shellfish",
            "habit": "Morning-bird",
            "work": "Work-from-home"
        },
        "phone_number": "2788591350",
        "bio": "Chance wife region contain necessary case rest. Officer interesting service star produce style chair. Surface agency consumer beautiful.",
        "liked_properties": [
            "218436886",
            "219244202",
            "219168271",
            "219238541",
            "21980702",
            "25643387",
            "25616660",
            "214435847",
            "219173928",
            "219175427",
            "22076152",
            "25644743",
            "219253546",
            "219139065",
            "25641346",
            "219249623",
            "219231982",
            "219207255",
            "219085079",
            "219143944",
            "219239631",
            "219193754",
            "219198852",
            "217022343",
            "23894825",
            "29106331",
            "219193752",
            "216023256",
            "218790911",
            "217613262",
            "218643402",
            "219149614",
            "214120484",
            "25631866",
            "219164565",
            "213841931",
            "219106047",
            "219236237",
            "219180760",
            "25640714",
            "219230190",
            "21980257",
            "25644878",
            "213841930",
            "216999293"
        ],
        "liked_users": [
            "79628573",
            "63202278",
            "40324675",
            "36947249",
            "99037340",
            "34735821"
        ]
    },
    {
        "firebase_id": "jbU2I0Av",
        "name": "Jacob Martinez",
        "profile_pic": "https://i.pinimg.com/originals/2f/15/f2/2f15f2e8c688b3120d3d26467b06330c.jpg",
        "selected_tags": {
            "language": [
                "French",
                "Chinese"
            ],
            "smoker": "Social smoker",
            "pets": "Cat-friendly",
            "diet": "Vegetarian",
            "allergies": "Peanuts",
            "habit": "Night-owl",
            "work": "Night-worker"
        },
        "phone_number": "488-219-8159x4975",
        "bio": "Listen organization who security strategy use.\nPass federal plant. Half part it student and. Dream increase structure sell open message ok.",
        "liked_properties": [
            "23103565",
            "218583076",
            "28267269",
            "25608713",
            "219176117",
            "219131395",
            "219200852",
            "217218304",
            "25639624",
            "218882242",
            "25587062",
            "218782792",
            "219230184",
            "217138596",
            "219210978",
            "219226498",
            "219239631",
            "216068290",
            "219160451",
            "25647510",
            "219198852",
            "218697840",
            "219111439",
            "213917019",
            "219243599",
            "218176856",
            "219226907",
            "25562992",
            "218643401",
            "219247322",
            "219226895",
            "213841929",
            "219229581",
            "219190717",
            "25647588",
            "25631670",
            "21980258",
            "217310263",
            "219231313",
            "25604975",
            "219178847",
            "25598088",
            "219197679",
            "25640164",
            "219239612",
            "219236237"
        ],
        "liked_users": []
    },
    {
        "firebase_id": "gX9QnUfX",
        "name": "Steven Neal",
        "profile_pic": "https://i.pinimg.com/originals/2f/15/f2/2f15f2e8c688b3120d3d26467b06330c.jpg",
        "selected_tags": {
            "language": [
                "Chinese"
            ],
            "smoker": "Non-smoker",
            "pets": "Dog-friendly",
            "diet": "Vegetarian",
            "allergies": "Shellfish",
            "habit": "Morning-bird",
            "work": "Night-worker"
        },
        "phone_number": "+1-623-843-4501x187",
        "bio": "Ten course say responsibility available fish. Media author star item tend simply agent.\nPoor job century especially. Close laugh six sport information. Contain weight business those himself rich.",
        "liked_properties": [
            "219038703",
            "219030928",
            "219225925",
            "219246637",
            "218130771",
            "217999289",
            "25647277",
            "214224437",
            "219100209",
            "219111439",
            "216023732",
            "25644878",
            "219070235",
            "218911735",
            "219246013",
            "25352704",
            "25646911",
            "217917052",
            "219246023",
            "219113269",
            "219226899",
            "25630865",
            "219226851",
            "219128719",
            "219231982",
            "218838139",
            "25646015",
            "26577786",
            "219143967",
            "219178846",
            "219143401",
            "219223872",
            "25647491",
            "219236230",
            "219229581",
            "219043856",
            "219105127",
            "217310275",
            "219199510"
        ],
        "liked_users": [
            "45245592",
            "90260480",
            "79848822",
            "19183683",
            "38132979"
        ]
    },
    {
        "firebase_id": "JjxbBedA",
        "name": "Anthony Cantrell",
        "profile_pic": "https://i.pinimg.com/originals/2f/15/f2/2f15f2e8c688b3120d3d26467b06330c.jpg",
        "selected_tags": {
            "language": [
                "French",
                "Chinese",
                "Hindi"
            ],
            "smoker": "Non-smoker",
            "pets": "Dog-friendly",
            "diet": "Vegan",
            "allergies": "Peanuts",
            "habit": "Morning-bird",
            "work": "Work-from-home"
        },
        "phone_number": "594.915.9870x631",
        "bio": "Environment pressure owner small morning red reflect. Measure leader new store trade.",
        "liked_properties": [
            "219214583",
            "218792247",
            "218882242",
            "219060062",
            "219200852",
            "218836926"
        ],
        "liked_users": [
            "33159011",
            "63254617",
            "93214393",
            "53246152"
        ]
    },
    {
        "firebase_id": "SBozOuEd",
        "name": "David Johnson",
        "profile_pic": "https://i.pinimg.com/originals/2f/15/f2/2f15f2e8c688b3120d3d26467b06330c.jpg",
        "selected_tags": {
            "language": [
                "English"
            ],
            "smoker": "Social smoker",
            "pets": "Cat-friendly",
            "diet": "Vegan",
            "allergies": "Peanuts",
            "habit": "Night-owl",
            "work": "Work-from-home"
        },
        "phone_number": "536-901-7305",
        "bio": "Challenge son check single large.\nShow five pattern product reveal plan environmental chance. Visit protect owner stay national physical happy book. Through central she because think.",
        "liked_properties": [
            "217218304",
            "218894015"
        ],
        "liked_users": [
            "76444534",
            "34610862",
            "25043107",
            "51598852",
            "45829718"
        ]
    },
    {
        "firebase_id": "uYpZs21f",
        "name": "Judith Perez",
        "profile_pic": "https://i.pinimg.com/originals/2f/15/f2/2f15f2e8c688b3120d3d26467b06330c.jpg",
        "selected_tags": {
            "language": [
                "Spanish"
            ],
            "smoker": "Smoker",
            "pets": "Cat-friendly",
            "diet": "Vegan",
            "allergies": "Shellfish",
            "habit": "Morning-bird",
            "work": "Work-from-home"
        },
        "phone_number": "623-892-8999",
        "bio": "Season them point message ball. Loss enjoy discover require me. Professor return during end year like.\nEverybody in choose wish.",
        "liked_properties": [
            "219131395",
            "219185080",
            "219232130",
            "218643400",
            "25636335",
            "218717254",
            "25644743",
            "25638122",
            "25604975",
            "219231982",
            "219010524",
            "26226464",
            "219217204",
            "219247317",
            "219255776",
            "219085079",
            "219203631",
            "217947237",
            "219118618",
            "218965253",
            "219234823",
            "219233234"
        ],
        "liked_users": [
            "19084941",
            "98237696",
            "79591501",
            "46805066",
            "49758229",
            "18333077"
        ]
    }
]